{
  "platform": "tiktok",
  "module": "products",
  "endpoint_name": "categories",
  "version": "202309",
  "summary": "Retrieve the list of product categories available for your shop",
  "description": "Retrieve the list of product categories available for your shop. Product categories are updated frequently, so it's recommended to call the API in real time to ensure you are using the latest category data. Caching category data locally may result in using outdated information, leading to errors when creating products. For the Indonesia market: To list a product on both TikTok Shop and Tokopedia, you must use only categories that are available on both platforms. Please call this API twice to identify the overlapping categories. Version\n202309\n  \nAPI Testing Tool",
  "path": "/product/202309/categories",
  "http_method": [
    "GET"
  ],
  "parameters": {
    "path": [],
    "query": [
      {
        "properties": "shop_cipher Required",
        "type": "string",
        "description": "Use this property to pass shop information in requesting the API. Failure in passing the correct value when requesting the API for cross-border shops will return incorrect response.  Get by API Get Authorization Shop"
      },
      {
        "properties": "app_key Required",
        "type": "string",
        "description": "Every single app will have a unique key. Please use the specific key assigned to your app."
      },
      {
        "properties": "sign Required",
        "type": "string",
        "description": "Signature generated by gen algorithm. When you send API requests to TTS, you must sign them so that TTS can identify the senders."
      },
      {
        "properties": "timestamp Required",
        "type": "int",
        "description": "Unix timestamp GMT (UTC+00:00). This timestamp is used across all API requests. Developers can use this convert to local time."
      },
      {
        "properties": "locale",
        "type": "string",
        "description": "The BCP-47 locale codes for displaying category information. Default: The default locale of your shop. Possible values: - de-DE - en-GB - en-IE - en-US - es-ES - es-MX - fr-FR - id-ID - it-IT - ja-JP - ms-MY - pt-BR - th-TH - vi-VN - zh-CN"
      },
      {
        "properties": "keyword",
        "type": "string",
        "description": "Filter categories by this keyword in local_name."
      },
      {
        "properties": "category_version",
        "type": "string",
        "description": "Filter categories by the category tree version. Possible values based on region: - US: v2, represents the 7-level category tree. Important: For US shops, you must pass v2 when using this API. - Other regions: v1, represents the 3-level category tree. Default: v1"
      },
      {
        "properties": "listing_platform",
        "type": "string",
        "description": "Filter categories by the specified platform. Possible values: - TIKTOK_SHOP - TOKOPEDIA Default: TIKTOK_SHOP  Applicable only for sellers that migrated from Tokopedia."
      },
      {
        "properties": "include_prohibited_categories",
        "type": "bool",
        "description": "A flag to indicate whether to include categories that are prohibited on TikTok Shop. Set this to true to identify which are the product categories that you can't list on TikTok Shop in any circumstances. Applicable only for BR, MX, EU and SEA markets."
      }
    ],
    "header": [
      {
        "properties": "content-type Required",
        "type": "string",
        "description": "Allowed type: application/json"
      },
      {
        "properties": "x-tts-access-token Required",
        "type": "string",
        "description": "The seller access_token value from Get Access Token, when user_type = 0. Follow this guide to get seller access_token."
      }
    ],
    "body": [],
    "common": []
  },
  "request_examples": [],
  "response": {
    "schema": [
      {
        "properties": "code",
        "type": "int",
        "description": "The success or failure status code returned in API response."
      },
      {
        "properties": "message",
        "type": "string",
        "description": "The success or failure messages returned in API response. Reasons of failure will be described in the message."
      },
      {
        "properties": "request_id",
        "type": "string",
        "description": "Request log"
      },
      {
        "properties": "data",
        "type": "object",
        "description": "Specific return information",
        "children": [
          {
            "properties": "categories",
            "type": "[]object",
            "description": "The list of categories that meet the query conditions.",
            "children": [
              {
                "properties": "id",
                "type": "string",
                "description": "The category ID."
              },
              {
                "properties": "parent_id",
                "type": "string",
                "description": "The parent category ID.  For the root category, the parent ID is 0."
              },
              {
                "properties": "local_name",
                "type": "string",
                "description": "The name of the category in the country where the shop operates."
              },
              {
                "properties": "is_leaf",
                "type": "bool",
                "description": "A flag to indicate if the category is a leaf category.   Note: You can only create or edit products that belong to a leaf category."
              },
              {
                "properties": "permission_statuses",
                "type": "[]string",
                "description": "The shop's permission status for this category. Possible values: - AVAILABLE: You have the permission to create products in this category. - INVITE_ONLY: This is a restricted category and you do not have permission to use it. Submit an application through the Qualification Center on TikTok Shop Seller Center to gain access. In Seller Center, INVITE_ONLY is also known as \"restricted\". - NON_MAIN_CATEGORY: This category is out of scope for this shop, and you do not have permission to use it. Contact your account manager for assistance. - PROHIBITED: This category is prohibited on TikTok Shop. Do not attempt to list products in this category as they will be rejected during audit. Applicable only for BR, MX, EU and SEA markets."
              }
            ]
          }
        ]
      }
    ],
    "examples": [
      {
        "language": "json",
        "code": "{\n  \"code\": 0,\n  \"data\": {\n    \"categories\": [\n      {\n        \"id\": \"600002\",\n        \"parent_id\": \"600001\",\n        \"local_name\": \"Home Supplies\",\n        \"is_leaf\": false,\n        \"permission_statuses\": [\n          \"INVITE_ONLY\",\n          \"NON_MAIN_CATEGORY\"\n        ]\n      }\n    ]\n  },\n  \"message\": \"Success\",\n  \"request_id\": \"202203070749000101890810281E8C70B7\"\n}"
      }
    ]
  },
  "error_codes": [
    {
      "code": "12052023",
      "message": "Category does not exist"
    },
    {
      "code": "12052217",
      "message": "Incorrect category version. For US shops or global sellers with an active US shop, specify 'category version=v2'. For shops in other regions specify 'category_version=v1'."
    },
    {
      "code": "12052230",
      "message": "The specified category ID is not a leaf category, or it does not belong to the specified category version. Note: For US shops or global sellers with an active US shop, specify 'category_version=v2'. For shops in other regions, specify 'category_version=v1'. Use the Get Categories/Get Global Categories endpoint to check the leaf categories that belong to the required category version."
    },
    {
      "code": "12052700",
      "message": "seller is inactived"
    },
    {
      "code": "12052704",
      "message": "seller id not exist"
    },
    {
      "code": "12052900",
      "message": "System error, try again later"
    }
  ],
  "platform_specific": {
    "original_url": "https://partner.tiktokshop.com/docv2/page/6509c89d0fcef602bf1acd9b"
  }
}