{
  "title": "Replicate Product",
  "content": "# Path: /product/202507/products/{product_id}/global_replicate\n# Method: [POST]\n# Function Description\nDescription of [POST]/product/:version/Replicate_Product\n\n---\n\n\n# Common Parameters\nFor common parameters, refer to [How to call TikTok Shop APIs - Common Parameters](https://partner.tiktokshop.com/docv2/page/64f199679495ef0281851ee5#Back%20To%20Top)\n| Properties <!-- width:110px --> | Location <!-- width:75px --> | Type <!-- width:75px --> | Require <!-- width:60px --> | Sample <!-- width:254px --> | Properties description <!-- width:254px --> |\n| --- | --- | --- | --- | --- | --- |\n| shop_cipher | query | string | Y | GCP_XF90igAAAABh00qsWgtvOiGFNqyubMt3 | Use this property to pass shop information in requesting the API. Failure in passing the correct value when requesting the API for cross-border shops will return incorrect response. |\n| Get by API [Get Authorization Shop](https://partner.tiktokshop.com/docv2/page/6507ead7b99d5302be949ba9?external_id=6507ead7b99d5302be949ba9) |  |  |  |  |  |\n| content-type | header | string | Y | application/json | Allowed type: application/json |\n# Request Path Parameters\n| Properties <!-- width:110px --> | Type <!-- width:90px --> | Require <!-- width:90px --> | Sample <!-- width:254px --> | Properties description <!-- width:254px --> |\n| --- | --- | --- | --- | --- |\n| product_id | string | Y | 1729592969712207008 | The product ID in TikTok Shop. |\n# Request Query Parameters\n| Properties <!-- width:110px --> | Type <!-- width:90px --> | Require <!-- width:90px --> | Sample <!-- width:254px --> | Properties description <!-- width:254px --> |\n| --- | --- | --- | --- | --- |\n| app_key | string | Y | 38abcd | Every single app will have a unique key. Please use the specific key assigned to your app. |\n| sign | string | Y | 5361235029d141222525e303d742f9e38aea052d10896d3197ab9d6233730b8c | Signature generated by gen algorithm. When you send API requests to TTS, you must sign them so that TTS can identify the senders. |\n| timestamp | int | Y | 1623812664 | Unix timestamp GMT (UTC+00:00). This timestamp is used across all API requests. Developers can use this convert to local time. |\n# Request Body Parameters\n| Properties <!-- width:110px --> | Type <!-- width:90px --> | Require <!-- width:90px --> | Sample <!-- width:254px --> | Properties description <!-- width:254px --> |\n| --- | --- | --- | --- | --- |\n| replicate_target | []object | N |  | Target markets for replicating the local product. |\n| ^region | string | N | US | The new market where you want to replicate the product. |\n| ^skus | []object | N |  | The SKUs to be published in the specified market. |\n\n* Max SKUs for EU, JP, UK, US: 300\n* Max SKUs for other regions: 100\n   Note: SKUs of all source country must be included. |\n   ^^source_sku_id |string |N |1732057700058170433 |The ID of the SKU being replicated |\n   ^^price |object |N | |The SKU's **local display price** shown on the product page before any discounts. |\n   ^^^currency |string |N |EUR |The currency. You must specify the local currency in the target market. |\n   ^^^sale_price |string |Y |100 |The SKU's local display price shown on the product page before any discounts.\n   Refer to Product Pricing for the allowed price ranges in each market. |\n   ^^inventory |[]object |N | |SKU inventory information per warehouse.\n   This field is only required if the inventory allocation mode for the warehouse is MANUAL. Otherwise, it is optional. |\n   ^^^warehouse_id |string |N |1732057700058170433 |The warehouse ID. Retrieve this value from the [Get Warehouse List API](650aa418defece02be6e66b6) or Get Inventory Rules API. |\n   ^^^quantity |int |N |100 |The SKU quantity available in the warehouse.\n   Valid range: [1, 999,999] |\n\n# Request Sample\n**Query**\n```Plain Text\nhttps://open-api.tiktokglobalshop.com/product/202507/products/1729592969712207008/global_replicate?app_key=123abc&sign=5361235029d141222525e303d742f9e38aea052d10896d3197ab9d6233730b8c&timestamp=1625484268&shop_cipher=ROW_RHkDDABBAAB8tKAVoAqsMTjsQZFLyNfY\n```\n\n**Body**\n```json\n{\"replicate_target\":[{\"region\":\"US\",\"skus\":[{\"source_sku_id\":\"1732057700058170433\",\"price\":{\"currency\":\"EUR\",\"sale_price\":\"100\"},\"inventory\":[{\"warehouse_id\":\"1732057700058170433\",\"quantity\":100}]}]}]}\n```\n\n# Response Parameters\n| Properties <!-- width:110px --> | Type <!-- width:90px --> | Sample <!-- width:289px --> | Properties description <!-- width:289px --> |\n| --- | --- | --- | --- |\n| code | int | 0 | The success or failure status code returned in API response. |\n| message | string | Success | The success or failure messages returned in API response. Reasons of failure will be described in the message. |\n| request_id | string | 202203070749000101890810281E8C70B7 | Request log |\n| data | object |  | Specific return information |\n| ^errors | []object |  | The list of errors that occurred. |\n| ^^code | int | 12052223 | The error code. |\n| ^^message | string | the category is unauthorized. | The error message. |\n| ^^detail | object |  | The details of the error. |\n| ^^^region | string | US | The target region where the error occurred. |\n# Response Sample\n```json\n{\"code\":0,\"data\":{\"errors\":[{\"code\":12052223,\"message\":\"the category is unauthorized.\",\"detail\":{\"region\":\"US\"}}]},\"message\":\"Success\",\"request_id\":\"202203070749000101890810281E8C70B7\"}\n```\n\n# Error Code\nFor common error codes, refer to [How to call TikTok Shop APIs - Common Error Code](https://partner.tiktokshop.com/docv2/page/64f199679495ef0281851ee5#Back%20To%20Top)\n| Code <!-- width:250px --> | Message <!-- width:553px --> |\n| --- | --- |\n\n",
  "update_time": "1757331436",
  "view_count": 0,
  "prev_document_id": "68a6847a5a65b904aba10374",
  "prev_document_path": "get-global-listing-rules-202507",
  "next_document_id": "68a685e65a65b904aba10cbf",
  "next_document_path": "get-global-replicated-products-202507",
  "is_api_doc": true,
  "document_id": "68a685ce5a65b904aba10b1a",
  "doc_type": 1,
  "keywords": [
    {
      "keyword": "",
      "font_color": "#141414",
      "background_color": "#E6E6E6"
    }
  ]
}