{
  "title": "Lazada\u670d\u52a1\u5e02\u573a\u5165\u9a7b\u64cd\u4f5c\u6307\u5f15",
  "category": "quick-start-guide",
  "language": "en",
  "document_id": 121773,
  "original_url": "https://open.lazada.com/doc/doc?docId=121773&nodeId=10533",
  "raw_file": "/home/lazykern/lab/ecommerce-api-docs/data/raw/lazada/guides/quick-start-guide/lazada.json",
  "markdown_file": "/home/lazykern/lab/ecommerce-api-docs/data/processed/lazada/guides/quick-start-guide/lazada.md",
  "html_length": 15988,
  "last_modified": "2024-09-24 17:22:54",
  "views": 1833,
  "tags": [],
  "author": "WB965441"
}